MANIFEST.in
setup.cfg
setup.py
discourse_django_sso/__init__.py
discourse_django_sso/admin.py
discourse_django_sso/apps.py
discourse_django_sso/models.py
discourse_django_sso/utils.py
discourse_django_sso/views.py
discourse_django_sso.egg-info/PKG-INFO
discourse_django_sso.egg-info/SOURCES.txt
discourse_django_sso.egg-info/dependency_links.txt
discourse_django_sso.egg-info/requires.txt
discourse_django_sso.egg-info/top_level.txt
discourse_django_sso/migrations/__init__.py
discourse_django_sso_test/__init__.py
discourse_django_sso_test/conftest.py
discourse_django_sso_test/test_base_sso.py
discourse_django_sso_test/test_sso_client.py
discourse_django_sso_test/test_sso_producer.py
discourse_django_sso_test/test_view.py
discourse_django_sso_test_project/__init__.py
discourse_django_sso_test_project/settings.py
discourse_django_sso_test_project/urls.py
discourse_django_sso_test_project/wsgi.py
requirements/base.in
requirements/base.txt
requirements/dev.in
requirements/dev.txt