Metadata-Version: 1.1
Name: discourse-django-sso
Version: 0.9.1
Summary: A Discourse sso app for Django
Home-page: UNKNOWN
Author: Jacek Bzdak
Author-email: jacek@askesis.pl
License: Apache 2.0
Platform: UNKNOWN
Classifier: Development Status :: 4 - Beta
Classifier: Environment :: Web Environment
Classifier: Framework :: Django :: 1.11
Classifier: Intended Audience :: Developers
Classifier: License :: OSI Approved :: Apache Software License
Classifier: Programming Language :: Python :: 3.5
